CHANGELOG.md
LICENSE
README.md
pyproject.toml
wagtailsitecheck/__init__.py
wagtailsitecheck/defaults.py
wagtailsitecheck/wagtail_hooks.py
wagtailsitecheck/management/__init__.py
wagtailsitecheck/management/commands/__init__.py
wagtailsitecheck/management/commands/checksites.py
wagtailsitecheck/management/commands/fixsites.py
wagtailsitecheck/templates/wagtailsitecheck/site_check_notification.html
wagtail_site_check-0.0.3.dist-info/METADATA
wagtail_site_check-0.0.3.dist-info/WHEEL
wagtail_site_check-0.0.3.dist-info/licenses/LICENSE
wagtail_site_check-0.0.3.dist-info/RECORD
